remeq/MessageQueue.py
remeq/__init__.py
remeq-1.0.0.dist-info/LICENSE.txt
remeq-1.0.0.dist-info/METADATA
remeq-1.0.0.dist-info/WHEEL
remeq-1.0.0.dist-info/top_level.txt
remeq-1.0.0.dist-info/RECORD
