Metadata-Version: 2.1
Name: remeq
Version: 1.0.0
Summary: A simple library for creating message queue based on Redis and its channels
Home-page: https://github.com/AndrewLt/remeq
Author: AndrewLt
License: MIT
Keywords: redis,queue,message
Classifier: License :: OSI Approved :: MIT License
Classifier: Programming Language :: Python :: 3.9
Classifier: Operating System :: OS Independent
Requires-Python: >=3.9
License-File: LICENSE.txt
Requires-Dist: redis >=5.0.0
Requires-Dist: hiredis
